{
  "internal": 678,
  "form": 1,
  "expGrowth": 0,
  "catchRate": 75,
  "gender": [2, 0],
  "baseFriendship": 50,
  "evoStage": 2,
  "evYield": [0, 0, 0, 0, 0, 2],
  "evolutions": [],
  "movesLevelUp": [
    {
      "level": 1,
      "levelPlus": 10,
      "move": 33
    },
    {
      "level": 1,
      "levelPlus": 10,
      "move": 43
    },
    {
      "level": 1,
      "levelPlus": 10,
      "move": 345
    },
    {
      "level": 1,
      "levelPlus": 10,
      "move": 574
    },
    {
      "level": 9,
      "levelPlus": 12,
      "move": 93
    },
    {
      "level": 13,
      "levelPlus": 16,
      "move": 313
    },
    {
      "level": 15,
      "levelPlus": 18,
      "move": 129
    },
    {
      "level": 21,
      "levelPlus": 24,
      "move": 60
    },
    {
      "level": 24,
      "levelPlus": 27,
      "move": 399
    },
    {
      "level": 30,
      "levelPlus": 33,
      "move": 113
    },
    {
      "level": 30,
      "levelPlus": 33,
      "move": 115
    },
    {
      "level": 36,
      "levelPlus": 39,
      "move": 473
    },
    {
      "level": 40,
      "levelPlus": 43,
      "move": 247
    },
    {
      "level": 44,
      "levelPlus": 47,
      "move": 94
    },
    {
      "level": 50,
      "levelPlus": 53,
      "move": 248
    }
  ],
  "movesTM": [
    {
      "index": 3,
      "move": 473
    },
    {
      "index": 6,
      "move": 347
    },
    {
      "index": 8,
      "move": 86
    },
    {
      "index": 16,
      "move": 113
    },
    {
      "index": 17,
      "move": 182
    },
    {
      "index": 20,
      "move": 583
    },
    {
      "index": 26,
      "move": 412
    },
    {
      "index": 27,
      "move": 129
    },
    {
      "index": 28,
      "move": 91
    },
    {
      "index": 31,
      "move": 115
    },
    {
      "index": 35,
      "move": 203
    },
    {
      "index": 41,
      "move": 352
    },
    {
      "index": 44,
      "move": 63
    },
    {
      "index": 51,
      "move": 219
    },
    {
      "index": 52,
      "move": 414
    },
    {
      "index": 55,
      "move": 416
    },
    {
      "index": 59,
      "move": 428
    },
    {
      "index": 60,
      "move": 248
    },
    {
      "index": 63,
      "move": 94
    },
    {
      "index": 67,
      "move": 85
    },
    {
      "index": 74,
      "move": 247
    },
    {
      "index": 83,
      "move": 417
    },
    {
      "index": 85,
      "move": 164
    },
    {
      "index": 90,
      "move": 399
    },
    {
      "index": 103,
      "move": 526
    }
  ],
  "description": "性格要比雄性更任性一些，而且也更具攻击性。要是惹得它不高兴，就会被它用精神力量狠狠教训。"
}
