{
  "pokemonLevelUp": [
    {
      "fullId": "004-0",
      "level": 12
    },
    {
      "fullId": "005-0",
      "level": 12
    },
    {
      "fullId": "006-0",
      "level": 12
    },
    {
      "fullId": "006-1",
      "level": 12
    },
    {
      "fullId": "006-2",
      "level": 12
    },
    {
      "fullId": "095-0",
      "level": 12
    },
    {
      "fullId": "208-0",
      "level": 12
    },
    {
      "fullId": "208-1",
      "level": 12
    },
    {
      "fullId": "333-0",
      "level": 20
    },
    {
      "fullId": "334-0",
      "level": 20
    },
    {
      "fullId": "334-1",
      "level": 20
    },
    {
      "fullId": "371-0",
      "level": 10
    },
    {
      "fullId": "372-0",
      "level": 10
    },
    {
      "fullId": "373-0",
      "level": 10
    },
    {
      "fullId": "373-1",
      "level": 10
    },
    {
      "fullId": "443-0",
      "level": 12
    },
    {
      "fullId": "444-0",
      "level": 12
    },
    {
      "fullId": "445-0",
      "level": 12
    },
    {
      "fullId": "445-1",
      "level": 12
    },
    {
      "fullId": "704-0",
      "level": 10
    },
    {
      "fullId": "705-0",
      "level": 10
    },
    {
      "fullId": "705-1",
      "level": 10
    },
    {
      "fullId": "706-0",
      "level": 10
    },
    {
      "fullId": "706-1",
      "level": 10
    },
    {
      "fullId": "718-0",
      "level": 1
    },
    {
      "fullId": "718-1",
      "level": 1
    },
    {
      "fullId": "718-2",
      "level": 1
    },
    {
      "fullId": "718-3",
      "level": 1
    },
    {
      "fullId": "718-4",
      "level": 1
    },
    {
      "fullId": "718-5",
      "level": 1
    },
    {
      "fullId": "780-0",
      "level": 20
    },
    {
      "fullId": "780-1",
      "level": 20
    }
  ],
  "pokemonTM": []
}